MANIFEST.in
README.md
VERSION
requirements.txt
setup.py
dfp_sync/__init__.py
dfp_sync/common.py
dfp_sync/utils.py
dfp_sync.egg-info/PKG-INFO
dfp_sync.egg-info/SOURCES.txt
dfp_sync.egg-info/dependency_links.txt
dfp_sync.egg-info/entry_points.txt
dfp_sync.egg-info/namespace_packages.txt
dfp_sync.egg-info/not-zip-safe
dfp_sync.egg-info/requires.txt
dfp_sync.egg-info/top_level.txt
dfp_sync/cli/__init__.py
dfp_sync/cli/cmd_service.py