Metadata-Version: 1.1
Name: dfp-sync
Version: 0.4.3
Summary: Sync Google DFP Data to S3 in hive-friendly formats.
Home-page: http://github.com/voxmedia/dfp-sync
Author: Brian Abelson
Author-email: brian.abelson@voxmedia.com
License: MIT
Platform: UNKNOWN
Classifier: Development Status :: 3 - Alpha
Classifier: Intended Audience :: Developers
Classifier: License :: OSI Approved :: MIT License
Classifier: Operating System :: OS Independent
Classifier: Programming Language :: Python
